hereapi/__init__.py
hereapi-0.0.1.dist-info/METADATA
hereapi-0.0.1.dist-info/RECORD
hereapi-0.0.1.dist-info/WHEEL
hereapi-0.0.1.dist-info/top_level.txt
