Metadata-Version: 2.1
Name: hereapi
Version: 0.0.1
Summary: A small example package
Home-page: https://github.com/sergiolucero/hereapi
Author: Sergio Lucero
Author-email: sergiolucero@gmail.com
License: UNKNOWN
Platform: UNKNOWN
Classifier: Programming Language :: Python :: 3
Classifier: License :: OSI Approved :: MIT License
Classifier: Operating System :: OS Independent
Requires-Dist: requests
Requires-Dist: folium
